{"config":{"output_file":null,"full_docs":false,"pub_only":true,"reachable_only":true,"distro_crate":false,"signatures":false,"borrow_data":false},"version":"0.19.1","compilation":{"directory":"C:\\Users\\dragon\\.cargo\\registry\\src\\github.com-1ecc6299db9ec823\\serde_json-1.0.73","program":"C:\\Users\\dragon\\.rustup\\toolchains\\stable-x86_64-pc-windows-msvc\\bin\\rls.exe","arguments":["--crate-name","build_script_build","--edition=2018","C:\\Users\\dragon\\.cargo\\registry\\src\\github.com-1ecc6299db9ec823\\serde_json-1.0.73\\build.rs","--json=diagnostic-rendered-ansi","--crate-type","bin","--emit=dep-info,link","-C","embed-bitcode=no","-C","debuginfo=2","--cfg","feature=\"default\"","--cfg","feature=\"std\"","-C","metadata=7a032f6e7b45c716","-C","extra-filename=-7a032f6e7b45c716","--out-dir","d:\\job\\cosmwasm\\cw721-main\\target\\rls\\debug\\build\\serde_json-7a032f6e7b45c716","-L","dependency=d:\\job\\cosmwasm\\cw721-main\\target\\rls\\debug\\deps","--cap-lints","allow","--error-format=json","--sysroot","C:\\Users\\dragon\\.rustup/toolchains/stable-x86_64-pc-windows-msvc"],"output":"d:\\job\\cosmwasm\\cw721-main\\target\\rls\\debug\\build\\serde_json-7a032f6e7b45c716\\build_script_build-7a032f6e7b45c716.exe"},"prelude":{"crate_id":{"name":"build_script_build","disambiguator":[15279558145278350367,0]},"crate_root":"C:\\Users\\dragon\\.cargo\\registry\\src\\github.com-1ecc6299db9ec823\\serde_json-1.0.73","external_crates":[{"file_name":"C:\\Users\\dragon\\.cargo\\registry\\src\\github.com-1ecc6299db9ec823\\serde_json-1.0.73\\build.rs","num":1,"id":{"name":"std","disambiguator":[7449352764569583903,0]}},{"file_name":"C:\\Users\\dragon\\.cargo\\registry\\src\\github.com-1ecc6299db9ec823\\serde_json-1.0.73\\build.rs","num":2,"id":{"name":"core","disambiguator":[1631835697898691535,0]}},{"file_name":"C:\\Users\\dragon\\.cargo\\registry\\src\\github.com-1ecc6299db9ec823\\serde_json-1.0.73\\build.rs","num":3,"id":{"name":"compiler_builtins","disambiguator":[9301228628034177852,0]}},{"file_name":"C:\\Users\\dragon\\.cargo\\registry\\src\\github.com-1ecc6299db9ec823\\serde_json-1.0.73\\build.rs","num":4,"id":{"name":"rustc_std_workspace_core","disambiguator":[2093790580695599362,0]}},{"file_name":"C:\\Users\\dragon\\.cargo\\registry\\src\\github.com-1ecc6299db9ec823\\serde_json-1.0.73\\build.rs","num":5,"id":{"name":"alloc","disambiguator":[6737091961566752624,0]}},{"file_name":"C:\\Users\\dragon\\.cargo\\registry\\src\\github.com-1ecc6299db9ec823\\serde_json-1.0.73\\build.rs","num":6,"id":{"name":"libc","disambiguator":[5404310561352066988,0]}},{"file_name":"C:\\Users\\dragon\\.cargo\\registry\\src\\github.com-1ecc6299db9ec823\\serde_json-1.0.73\\build.rs","num":7,"id":{"name":"unwind","disambiguator":[1962508984173027375,0]}},{"file_name":"C:\\Users\\dragon\\.cargo\\registry\\src\\github.com-1ecc6299db9ec823\\serde_json-1.0.73\\build.rs","num":8,"id":{"name":"cfg_if","disambiguator":[6035099278034299636,0]}},{"file_name":"C:\\Users\\dragon\\.cargo\\registry\\src\\github.com-1ecc6299db9ec823\\serde_json-1.0.73\\build.rs","num":9,"id":{"name":"hashbrown","disambiguator":[2965237822319993894,0]}},{"file_name":"C:\\Users\\dragon\\.cargo\\registry\\src\\github.com-1ecc6299db9ec823\\serde_json-1.0.73\\build.rs","num":10,"id":{"name":"rustc_std_workspace_alloc","disambiguator":[18202861773354635365,0]}},{"file_name":"C:\\Users\\dragon\\.cargo\\registry\\src\\github.com-1ecc6299db9ec823\\serde_json-1.0.73\\build.rs","num":11,"id":{"name":"rustc_demangle","disambiguator":[5256087510298979761,0]}},{"file_name":"C:\\Users\\dragon\\.cargo\\registry\\src\\github.com-1ecc6299db9ec823\\serde_json-1.0.73\\build.rs","num":12,"id":{"name":"std_detect","disambiguator":[9054181207765082768,0]}},{"file_name":"C:\\Users\\dragon\\.cargo\\registry\\src\\github.com-1ecc6299db9ec823\\serde_json-1.0.73\\build.rs","num":13,"id":{"name":"panic_unwind","disambiguator":[15345473809858678681,0]}}],"span":{"file_name":"C:\\Users\\dragon\\.cargo\\registry\\src\\github.com-1ecc6299db9ec823\\serde_json-1.0.73\\build.rs","byte_start":0,"byte_end":1615,"line_start":1,"line_end":52,"column_start":1,"column_end":2}},"imports":[],"defs":[{"kind":"Mod","id":{"krate":0,"index":0},"span":{"file_name":"C:\\Users\\dragon\\.cargo\\registry\\src\\github.com-1ecc6299db9ec823\\serde_json-1.0.73\\build.rs","byte_start":0,"byte_end":1615,"line_start":1,"line_end":52,"column_start":1,"column_end":2},"name":"","qualname":"::","value":"C:\\Users\\dragon\\.cargo\\registry\\src\\github.com-1ecc6299db9ec823\\serde_json-1.0.73\\build.rs","parent":null,"children":[{"krate":0,"index":1},{"krate":0,"index":2},{"krate":0,"index":3},{"krate":0,"index":4},{"krate":0,"index":6},{"krate":0,"index":9},{"krate":0,"index":10},{"krate":0,"index":13},{"krate":0,"index":16},{"krate":0,"index":17}],"decl_id":null,"docs":"","sig":null,"attributes":[]}],"impls":[],"refs":[],"macro_refs":[],"relations":[]}